zyne/__init__.py
zyne/api.py
zyne/middleware.py
zyne/orm.py
zyne/response.py
zyne-1.0.0.dist-info/METADATA
zyne-1.0.0.dist-info/WHEEL
zyne-1.0.0.dist-info/top_level.txt
zyne-1.0.0.dist-info/RECORD
