Metadata-Version: 2.1
Name: zyne
Version: 1.0.0
Summary: Zyne: Python MVC Web Framework.
Home-page: UNKNOWN
Author: Gilberto albino
Author-email: framework@zyne.com.br
License: MIT
Platform: UNKNOWN
Classifier: Programming Language :: Python :: 3.10
Requires-Python: >=3.10.0
Requires-Dist: Jinja2 (==3.1.2)
Requires-Dist: WebOb (==1.8.7)
Requires-Dist: parse (==1.19.0)
Requires-Dist: requests-wsgi-adapter (==0.4.1)
Requires-Dist: requests (==2.28.1)
Requires-Dist: whitenoise (==6.2.0)
